wagtail_sitemap_seo/__init__.py
wagtail_sitemap_seo/admin_views.py
wagtail_sitemap_seo/apps.py
wagtail_sitemap_seo/base.py
wagtail_sitemap_seo/root_builder.py
wagtail_sitemap_seo/s3_helper.py
wagtail_sitemap_seo/storage.py
wagtail_sitemap_seo/sub_map_builder.py
wagtail_sitemap_seo/urls.py
wagtail_sitemap_seo/views.py
wagtail_sitemap_seo/wagtail_hooks.py
wagtail_sitemap_seo/management/__init__.py
wagtail_sitemap_seo/management/commands/__init__.py
wagtail_sitemap_seo/management/commands/build_sitemaps.py
wagtail_sitemap_seo/templates/wagtail_sitemap_seo/build_sitemaps_confirm.html
wagtail_sitemap_seo-1.5.1.dist-info/licenses/LICENSE
wagtail_sitemap_seo-1.5.1.dist-info/METADATA
wagtail_sitemap_seo-1.5.1.dist-info/WHEEL
wagtail_sitemap_seo-1.5.1.dist-info/top_level.txt
wagtail_sitemap_seo-1.5.1.dist-info/RECORD
