Metadata-Version: 2.4
Name: wagtail-sitemap-seo
Version: 1.5.1
Summary: Sitemap XML generation helpers for Wagtail
Author: Gerry Mcbride
License: MIT
Requires-Python: >=3.10
License-File: LICENSE
Requires-Dist: Django>=4.2
Requires-Dist: wagtail>=5.2
Dynamic: license-file
